dedoc/__init__.py
dedoc/config.py
dedoc/dedoc_manager.py
dedoc/download_models.py
dedoc/extensions.py
dedoc/main.py
dedoc/manager_config.py
dedoc/version.py
dedoc/api/__init__.py
dedoc/api/api_args.py
dedoc/api/api_utils.py
dedoc/api/cancellation.py
dedoc/api/dedoc_api.py
dedoc/api/process_handler.py
dedoc/api/schema/__init__.py
dedoc/api/schema/annotation.py
dedoc/api/schema/cell_with_meta.py
dedoc/api/schema/document_content.py
dedoc/api/schema/document_metadata.py
dedoc/api/schema/line_metadata.py
dedoc/api/schema/line_with_meta.py
dedoc/api/schema/parsed_document.py
dedoc/api/schema/table.py
dedoc/api/schema/table_metadata.py
dedoc/api/schema/tree_node.py
dedoc/attachments_extractors/__init__.py
dedoc/attachments_extractors/abstract_attachment_extractor.py
dedoc/attachments_extractors/concrete_attachments_extractors/__init__.py
dedoc/attachments_extractors/concrete_attachments_extractors/abstract_office_attachments_extractor.py
dedoc/attachments_extractors/concrete_attachments_extractors/docx_attachments_extractor.py
dedoc/attachments_extractors/concrete_attachments_extractors/excel_attachments_extractor.py
dedoc/attachments_extractors/concrete_attachments_extractors/json_attachment_extractor.py
dedoc/attachments_extractors/concrete_attachments_extractors/pdf_attachments_extractor.py
dedoc/attachments_extractors/concrete_attachments_extractors/pptx_attachments_extractor.py
dedoc/attachments_handler/__init__.py
dedoc/attachments_handler/attachments_handler.py
dedoc/common/__init__.py
dedoc/common/exceptions/__init__.py
dedoc/common/exceptions/bad_file_error.py
dedoc/common/exceptions/bad_parameters_error.py
dedoc/common/exceptions/conversion_error.py
dedoc/common/exceptions/dedoc_error.py
dedoc/common/exceptions/java_not_found_error.py
dedoc/common/exceptions/missing_file_error.py
dedoc/common/exceptions/recognize_error.py
dedoc/common/exceptions/structure_extractor_error.py
dedoc/common/exceptions/tabby_pdf_error.py
dedoc/converters/__init__.py
dedoc-2.6.1.dist-info/licenses/LICENSE.txt
dedoc-2.6.1.dist-info/METADATA
dedoc-2.6.1.dist-info/WHEEL
dedoc-2.6.1.dist-info/entry_points.txt
dedoc-2.6.1.dist-info/top_level.txt
dedoc-2.6.1.dist-info/RECORD
