Metadata-Version: 2.4
Name: dedoc
Version: 2.6.1
Summary: Extract content and logical tree structure from textual documents
Author-email: Dedoc team <dedoc@ispras.ru>
Maintainer-email: Oksana Belyaeva <belyaeva@ispras.ru>, Andrew Perminov <perminov@ispras.ru>, Anastasiya Bogatenkova <bogatenkova.anastasiya@mail.ru>
License: 
Project-URL: homepage, https://github.com/ispras/dedoc
Project-URL: repository, https://github.com/ispras/dedoc.git
Project-URL: documentation, https://dedoc.readthedocs.io
Project-URL: changelog, https://dedoc.readthedocs.io/en/latest/changelog.html
Keywords: document analysis,logical structure extraction,OCR,deep learning,computer vision
Classifier: Intended Audience :: Developers
Classifier: License :: OSI Approved :: Apache Software License
Classifier: Programming Language :: Python :: 3.8
Classifier: Programming Language :: Python :: 3.9
Classifier: Programming Language :: Python :: 3.10
Classifier: Programming Language :: Python :: 3 :: Only
Requires-Python: >=3.8
License-File: LICENSE.txt
Requires-Dist: beautifulsoup4<=4.12.3,>=4.10.0
Requires-Dist: charset-normalizer<=3.2.0,>=2.0.12
Requires-Dist: Cython<=3.0.2,>=0.29.28
Requires-Dist: dedoc-utils==0.3.8
Requires-Dist: fastapi<1.0,>=0.77.0
Requires-Dist: fontTools<5.0,>=4.0
Requires-Dist: huggingface-hub<1.0,>=0.14.1
Requires-Dist: imutils==0.5.4
Requires-Dist: itsdangerous<=2.1.2,>=2.1.0
Requires-Dist: levenshtein<1,>=0.12.2
Requires-Dist: numpy<2.0,>=1.22.0
Requires-Dist: olefile~=0.46
Requires-Dist: opencv-python<4.6.0,>=4.5.5.64
Requires-Dist: orjson<4.0,>=3.8.11
Requires-Dist: pandas<3,>=1.4.1
Requires-Dist: pdf.tocgen<=1.3.4,>=1.3.0
Requires-Dist: pdf2image==1.10.0
Requires-Dist: pdfminer.six<=20231228,>=20211012
Requires-Dist: piexif==1.1.3
Requires-Dist: puremagic<2.0,>=1.0
Requires-Dist: py7zr~=1.0
Requires-Dist: pypdf<6.0,>=4.0
Requires-Dist: pytesseract==0.3.10
Requires-Dist: python-docx==0.8.11
Requires-Dist: python-logstash-async<=2.7.0,>=2.5.0
Requires-Dist: python-magic<1.0
Requires-Dist: python-multipart==0.0.6
Requires-Dist: rarfile==4.0
Requires-Dist: requests>=2.22.0
Requires-Dist: roman<4.0,>=3.3
Requires-Dist: scikit-image<=0.21.0,>=0.19.3
Requires-Dist: scikit_learn<=1.2.2,>=1.0.2
Requires-Dist: scipy<=1.11.2,>=1.8.0
Requires-Dist: six<2.0,>=1.14.0
Requires-Dist: starlette<=0.27.0,>=0.26.1
Requires-Dist: texttable<2.0,>=1.6.7
Requires-Dist: ujson<=5.8.0,>=5.4.0
Requires-Dist: uvicorn<=0.23.2,>=0.18.0
Requires-Dist: wget==3.2
Requires-Dist: xgbfir<1.0,>=0.3.1
Requires-Dist: xgboost<2.0,>=1.6.0
Requires-Dist: xlrd<2.0,>=1.2.0
Provides-Extra: torch
Requires-Dist: torch~=1.11.0; extra == "torch"
Requires-Dist: torchvision~=0.12.0; extra == "torch"
Provides-Extra: docs
Requires-Dist: docutils==0.18.1; extra == "docs"
Requires-Dist: Sphinx==6.2.1; extra == "docs"
Requires-Dist: sphinx_rtd_theme==1.2.0; extra == "docs"
Requires-Dist: sphinx_copybutton==0.5.2; extra == "docs"
Requires-Dist: sphinx-togglebutton==0.3.2; extra == "docs"
Requires-Dist: linuxdoc==20230506; extra == "docs"
Requires-Dist: tabula-py==2.8.1; extra == "docs"
Requires-Dist: html2text==2024.2.26; extra == "docs"
Provides-Extra: lint
Requires-Dist: flake8==5.0.4; extra == "lint"
Requires-Dist: flake8-absolute-import==1.0.0.1; extra == "lint"
Requires-Dist: flake8-annotations==2.9.1; extra == "lint"
Requires-Dist: flake8-bugbear==23.3.12; extra == "lint"
Requires-Dist: flake8-builtins==2.1.0; extra == "lint"
Requires-Dist: flake8-fill-one-line>=0.4.2; extra == "lint"
Requires-Dist: flake8-import-order==0.18.2; extra == "lint"
Requires-Dist: flake8-multiline-containers==0.0.19; extra == "lint"
Requires-Dist: flake8-print==5.0.0; extra == "lint"
Requires-Dist: flake8-tidy-imports==4.10.0; extra == "lint"
Requires-Dist: flake8-quotes==3.3.2; extra == "lint"
Requires-Dist: flake8-use-fstring==1.4; extra == "lint"
Requires-Dist: pycodestyle==2.9.0; extra == "lint"
Requires-Dist: pep8-naming==0.13.3; extra == "lint"
Dynamic: license-file
